pyq/__init__.py
pyq/_k.pyd
pyq/_n.py
pyq/_pt_run.py
pyq/cmd.py
pyq/conftest.py
pyq/magic.py
pyq/ptk.py
pyq/version.py
pyq/tests/__init__.py
pyq/tests/test_ci.py
pyq/tests/test_com.py
pyq/tests/test_k.py
pyq/tests/test_magic.py
pyq/tests/test_memoryview.py
pyq/tests/test_n.py
pyq/tests/test_no_numpy.py
pyq/tests/test_numpy.py
pyq/tests/test_p.py
pyq/tests/test_pathlib.py
pyq/tests/test_pypath.py
pyq/tests/test_pyq_executable.py
pyq/tests/test_python_q.py
pyq/tests/test_q.py
pyq/tests/test_sd.py
pyq/tests/test_threads.py
pyq/tests/test_version.py
pyq-4.1.2.data/data/q/p.k
pyq-4.1.2.data/data/q/pyq-config.q
pyq-4.1.2.data/data/q/pyq-operators.q
pyq-4.1.2.data/data/q/python.q
pyq-4.1.2.data/data/q/w32/p.dll
pyq-4.1.2.data/scripts/ipyq
pyq-4.1.2.data/scripts/pq
pyq-4.1.2.data/scripts/pyq-coverage
pyq-4.1.2.data/scripts/pyq-runtests
pyq-4.1.2.data/scripts/qp
pyq-4.1.2.dist-info/DESCRIPTION.rst
pyq-4.1.2.dist-info/METADATA
pyq-4.1.2.dist-info/RECORD
pyq-4.1.2.dist-info/WHEEL
pyq-4.1.2.dist-info/metadata.json
pyq-4.1.2.dist-info/top_level.txt
